mseep_dicom_mcp-0.1.3.dist-info/licenses/LICENSE
tests/__init__.py
tests/test.py
tests/test_dicom_mcp.py
tests/test_dicom_move.py
tests/test_dicom_pdf.py
mseep_dicom_mcp-0.1.3.dist-info/METADATA
mseep_dicom_mcp-0.1.3.dist-info/WHEEL
mseep_dicom_mcp-0.1.3.dist-info/entry_points.txt
mseep_dicom_mcp-0.1.3.dist-info/top_level.txt
mseep_dicom_mcp-0.1.3.dist-info/RECORD
