Metadata-Version: 2.4
Name: mseep-dicom-mcp
Version: 0.1.3
Summary: Add your description here
Home-page: 
Author: mseep
Author-email: mseep <support@skydeck.ai>
Maintainer-email: mseep <support@skydeck.ai>
Requires-Python: >=3.6
License-File: LICENSE
Requires-Dist: httpx>=0.28.1
Requires-Dist: mcp[cli]>=1.3.0
Requires-Dist: pynetdicom>=2.1.1
Requires-Dist: pypdf2>=3.0.1
Requires-Dist: pyyaml>=6.0.2
Provides-Extra: dev
Requires-Dist: pytest>=7.4.0; extra == "dev"
Requires-Dist: requests>=2.31.0; extra == "dev"
Requires-Dist: pydicom>=2.4.0; extra == "dev"
Requires-Dist: pytest-cov>=6.0.0; extra == "dev"
Requires-Dist: reportlab; extra == "dev"
Dynamic: author
Dynamic: license-file
Dynamic: requires-python
